{
    "channelId": "1083393495907188786",
    "guildId": "794993889131626576",
    "id": "1083411988648050769",
    "createdTimestamp": 1678375946915,
    "type": 0,
    "system": false,
    "content": "",
    "author": {
      "id": "760456056366563358",
      "bot": false,
      "system": false,
      "flags":{},
      "username": "! Nausicaä",
      "discriminator": "8888",
      "avatar": "db95972b2ac29db8d708e877ddd41583",
      "banner": null,
      "accentColor": null
    },
    "pinned": false,
    "tts": false,
    "nonce": "1083411989562130432",
    "embeds": [],
    "components": [],
    "attachments": {},
    "stickers": {},
    "position": null,
    "editedTimestamp": null,
    "reactions":{ },
    "mentions": {
      "everyone": false,
      "users":  {},
      "roles":  {},
      "_members": null,
      "_channels": null,
      "_parsedUsers": null,
      "crosspostedChannels": {},
      "repliedUser": null
    },
    "webhookId": null,
    "groupActivityApplication": null,
    "applicationId": null,
    "activity": null,
    "flags": {},
    "reference": null,
    "interaction": null
  }